setup.py
chaos/__init__.py
chaos/arguments.py
chaos/cli.py
chaos/config.py
chaos/db.py
chaos/globber.py
chaos/logging.py
chaos/version.py
chaos.egg-info/PKG-INFO
chaos.egg-info/SOURCES.txt
chaos.egg-info/dependency_links.txt
chaos.egg-info/requires.txt
chaos.egg-info/top_level.txt
chaos/amqp/__init__.py
chaos/amqp/exceptions.py
chaos/amqp/exchange.py
chaos/amqp/queue.py
chaos/amqp/rpc.py
chaos/multiprocessing/__init__.py
chaos/multiprocessing/workers.py
chaos/threading/__init__.py
chaos/threading/scheduler.py
chaos/threading/threads.py