Metadata-Version: 1.1
Name: chaos
Version: 0.2.2
Summary: chaos Python modules: Assorted libraries and subroutines
Home-page: https://github.com/LordGaav/python-chaos
Author: Nick Douma
Author-email: n.douma@nekoconeko.nl
License: GNU LGPLv3+
Platform: any
Classifier: Development Status :: 4 - Beta
Classifier: Intended Audience :: Developers
Classifier: License :: OSI Approved :: GNU Lesser General Public License v3 or later (LGPLv3+)
Classifier: Operating System :: Unix
Classifier: Programming Language :: Python :: 2 :: Only
Classifier: Programming Language :: Python :: 2.7
Classifier: Topic :: Software Development :: Libraries :: Python Modules
